nearby/__init__.py
nearby/actions.py
nearby/config.py
nearby/exceptions.py
nearby-0.1.3.data/scripts/nearby
nearby-0.1.3.dist-info/DESCRIPTION.rst
nearby-0.1.3.dist-info/METADATA
nearby-0.1.3.dist-info/RECORD
nearby-0.1.3.dist-info/WHEEL
nearby-0.1.3.dist-info/metadata.json
nearby-0.1.3.dist-info/top_level.txt
