Metadata-Version: 2.0
Name: nearby
Version: 0.1.3
Summary: Simple, dumb interface to remote files
Home-page: Https://github.com/chucksmash/nearby.git
Author: Chuck Bassett
Author-email: iamchuckb@gmail.com
License: MIT
Keywords: sshfs fusemount remote nearby
Platform: UNKNOWN
Classifier: Development Status :: 4 - Beta
Classifier: Environment :: Console
Classifier: Intended Audience :: Developers
Classifier: License :: OSI Approved :: MIT License
Classifier: Natural Language :: English
Classifier: Operating System :: POSIX
Classifier: Operating System :: MacOS :: MacOS X
Classifier: Programming Language :: Python :: 3
